qrmark/__main__.py
cli_qr_watermark-0.1.0.dist-info/METADATA
cli_qr_watermark-0.1.0.dist-info/WHEEL
cli_qr_watermark-0.1.0.dist-info/entry_points.txt
cli_qr_watermark-0.1.0.dist-info/top_level.txt
cli_qr_watermark-0.1.0.dist-info/RECORD
