Metadata-Version: 2.4
Name: cli-qr-watermark
Version: 0.1.0
Summary: CLI tool to overlay semi-transparent QR codes on images
Author-email: nazgool87 <you@example.com>
License-Expression: MIT
Project-URL: Homepage, https://github.com/nazgool97/cli-qr-watermark
Requires-Dist: Pillow>=10
Requires-Dist: qrcode[pil]>=7
Requires-Dist: click>=8
Requires-Dist: rich>=13
